lxml-stubs/ElementInclude.pyi
lxml-stubs/__init__.pyi
lxml-stubs/_types.pyi
lxml-stubs/builder.pyi
lxml-stubs/cssselect.pyi
lxml-stubs/etree/__init__.pyi
lxml-stubs/etree/_classlookup.pyi
lxml-stubs/etree/_cleanup.pyi
lxml-stubs/etree/_docloader.pyi
lxml-stubs/etree/_dtd.pyi
lxml-stubs/etree/_element.pyi
lxml-stubs/etree/_factory_func.pyi
lxml-stubs/etree/_iterparse.pyi
lxml-stubs/etree/_module_func.pyi
lxml-stubs/etree/_module_misc.pyi
lxml-stubs/etree/_nsclasses.pyi
lxml-stubs/etree/_parser.pyi
lxml-stubs/etree/_relaxng.pyi
lxml-stubs/etree/_saxparser.pyi
lxml-stubs/etree/_serializer.pyi
lxml-stubs/etree/_xinclude.pyi
lxml-stubs/etree/_xmlerror.pyi
lxml-stubs/etree/_xmlid.pyi
lxml-stubs/etree/_xmlschema.pyi
lxml-stubs/etree/_xpath.pyi
lxml-stubs/etree/_xslt.pyi
lxml-stubs/html/__init__.pyi
lxml-stubs/html/_element.pyi
lxml-stubs/html/_form.pyi
lxml-stubs/html/_funcs.pyi
lxml-stubs/html/_parse.pyi
lxml-stubs/html/builder.pyi
lxml-stubs/html/clean.pyi
lxml-stubs/html/defs.pyi
lxml-stubs/html/diff.pyi
lxml-stubs/html/html5parser.pyi
lxml-stubs/html/soupparser.pyi
lxml-stubs/isoschematron.pyi
lxml-stubs/objectify/__init__.pyi
lxml-stubs/objectify/_annotate.pyi
lxml-stubs/objectify/_element.pyi
lxml-stubs/objectify/_factory.pyi
lxml-stubs/objectify/_misc.pyi
lxml-stubs/py.typed
lxml-stubs/sax.pyi
mypy_plugin_lxml/__init__.py
mypy_plugin_lxml/main.py
types_lxml_multi_subclass-2026.1.1.dist-info/METADATA
types_lxml_multi_subclass-2026.1.1.dist-info/WHEEL
types_lxml_multi_subclass-2026.1.1.dist-info/entry_points.txt
types_lxml_multi_subclass-2026.1.1.dist-info/licenses/LICENSE
types_lxml_multi_subclass-2026.1.1.dist-info/RECORD
