Metadata-Version: 2.4
Name: types-lxml-multi-subclass
Version: 2026.1.1
Summary: Complete lxml external type annotation
Keywords: lxml,typing,stubs,annotation
Author-Email: Abel Cheung <abelcheung@gmail.com>
License-Expression: Apache-2.0
License-File: LICENSE
Classifier: Development Status :: 5 - Production/Stable
Classifier: Programming Language :: Python
Classifier: Intended Audience :: Developers
Classifier: Programming Language :: Python :: 3 :: Only
Classifier: Programming Language :: Python :: 3.9
Classifier: Programming Language :: Python :: 3.10
Classifier: Programming Language :: Python :: 3.11
Classifier: Programming Language :: Python :: 3.12
Classifier: Programming Language :: Python :: 3.13
Classifier: Programming Language :: Python :: 3.14
Classifier: Typing :: Stubs Only
Classifier: Operating System :: OS Independent
Project-URL: homepage, https://github.com/abelcheung/types-lxml
Requires-Python: >=3.9
Requires-Dist: typing_extensions~=4.15
Requires-Dist: cssselect~=1.2
Requires-Dist: beautifulsoup4~=4.13
Requires-Dist: types-html5lib~=1.1.11.20250809
Provides-Extra: mypy
Requires-Dist: mypy>=1.18.1; extra == "mypy"
Provides-Extra: dev
Requires-Dist: tox~=4.24; extra == "dev"
Requires-Dist: html5lib==1.1; extra == "dev"
Requires-Dist: pook>=2.0; extra == "dev"
Requires-Dist: urllib3>=2.0; extra == "dev"
Requires-Dist: pytest<9,>=7.0; extra == "dev"
Requires-Dist: pytest-mypy-plugins>=3.2.0; extra == "dev"
Requires-Dist: pytest-revealtype-injector>=0.7.1; extra == "dev"
Requires-Dist: lxml>=5.0; extra == "dev"
Requires-Dist: rnc2rng; extra == "dev"
Requires-Dist: hypothesis>=6.127.7; extra == "dev"
Requires-Dist: tzdata; extra == "dev"
Requires-Dist: ruff~=0.6; extra == "dev"
Requires-Dist: mypy>=1.18.1; extra == "dev"
Requires-Dist: pyright>=1.1.406; extra == "dev"
Requires-Dist: basedpyright>=1.31.6; platform_machine != "i686" and extra == "dev"
Requires-Dist: ty>=0.0.7; extra == "dev"
Requires-Dist: pyrefly>=0.46.3; extra == "dev"
